withtray/__init__.py
withtray/main.py
withtray-0.1.1.dist-info/LICENSE
withtray-0.1.1.dist-info/METADATA
withtray-0.1.1.dist-info/WHEEL
withtray-0.1.1.dist-info/entry_points.txt
withtray-0.1.1.dist-info/top_level.txt
withtray-0.1.1.dist-info/RECORD
