Metadata-Version: 2.1
Name: withtray
Version: 0.1.1
Summary: Run any blocking command with systray icon
Home-page: https://github.com/krisfris/withtray
Author: Kris
Author-email: 31852063+krisfris@users.noreply.github.com
License: UNKNOWN
Platform: UNKNOWN
Requires-Dist: click
Requires-Dist: pygobject
Requires-Dist: Pillow
Requires-Dist: pystray
